core/__init__.py
core/hep.py
core/hepsub.py
core/hepsubnew.py
core/jobCandidates.py
core/util.py
core/walksearch.py
smartHepsub/__init__.py
smartHepsub/config.py
smartHepsub/hep.py
smartHepsub/hepsub.py
smartHepsub/jobCandidates.py
smartHepsub/util.py
smartHepsub/walksearch.py
SmartHepSub-1.1.dist-info/LICENSE
SmartHepSub-1.1.dist-info/METADATA
SmartHepSub-1.1.dist-info/WHEEL
SmartHepSub-1.1.dist-info/entry_points.txt
SmartHepSub-1.1.dist-info/top_level.txt
SmartHepSub-1.1.dist-info/RECORD
